missinglink/__init__.py
missinglink/crypto/__init__.py
missinglink/crypto/asymmetric.py
missinglink/crypto/azure_envelope.py
missinglink/crypto/azure_key_vault.py
missinglink/crypto/cipher.py
missinglink/crypto/envelope.py
missinglink/crypto/gcp_envelope.py
missinglink/crypto/gcp_kms.py
missinglink/crypto/kms.py
missinglink/crypto/kms_envelope.py
missinglink/crypto/multikey_envelope.py
missinglink/crypto/ssh_idnetity.py
missinglink/crypto/symmertric.py
missinglink/crypto/legacy/__init__.py
missinglink/crypto/legacy/aes_ctc.py
missinglink/crypto/legacy/kms_legacy_envelope.py
ml_crypto-0.7.811.dist-info/LICENSE
ml_crypto-0.7.811.dist-info/METADATA
ml_crypto-0.7.811.dist-info/WHEEL
ml_crypto-0.7.811.dist-info/top_level.txt
ml_crypto-0.7.811.dist-info/RECORD
